{
    "list": [
        {
            "src": "https://copyright.bdstatic.com/1676361048,825209148.jpg@w_640|wm_1,k_YmpoX3F1YW5qaW5nd2F0ZXIucG5n",
            "img_attr": "{\"width\":5472,\"height\":3080}"
        },
        {
            "src": "https://copyright.bdstatic.com/405716182,95316596.jpg@w_640|wm_1,k_YmpoX3F1YW5qaW5nd2F0ZXIucG5n",
            "img_attr": "{\"width\":3080,\"height\":5472}"
        },
        {
            "src": "https://copyright.bdstatic.com/2846103070,3781827681.jpg@w_640|wm_1,k_YmpoX3F1YW5qaW5nd2F0ZXIucG5n",
            "img_attr": "{\"width\":6000,\"height\":4000}"
        },
        {
            "src": "https://copyright.bdstatic.com/1943294447,3895319049.jpg@w_640|wm_1,k_YmpoX3F1YW5qaW5nd2F0ZXIucG5n",
            "img_attr": "{\"width\":5472,\"height\":3648}"
        },
        {
            "src": "https://copyright.bdstatic.com/2568846153,3769452646.jpg@w_640|wm_1,k_YmpoX3F1YW5qaW5nd2F0ZXIucG5n",
            "img_attr": "{\"width\":3264,\"height\":1836}"
        },
        {
            "src": "https://copyright.bdstatic.com/1488289117,977754164.jpg@w_640|wm_1,k_YmpoX3F1YW5qaW5nd2F0ZXIucG5n",
            "img_attr": "{\"width\":2832,\"height\":4256}"
        },
        {
            "src": "https://copyright.bdstatic.com/2094892804,4057844358.jpg@w_640|wm_1,k_YmpoX3F1YW5qaW5nd2F0ZXIucG5n",
            "img_attr": "{\"width\":2798,\"height\":2800}"
        },
        {
            "src": "https://copyright.bdstatic.com/2304233757,3233908082.jpg@w_640|wm_1,k_YmpoX3F1YW5qaW5nd2F0ZXIucG5n",
            "img_attr": "{\"width\":3024,\"height\":4032}"
        },
        {
            "src": "https://copyright.bdstatic.com/247898857,2531683181.jpg@w_640|wm_1,k_YmpoX3F1YW5qaW5nd2F0ZXIucG5n",
            "img_attr": "{\"width\":4208,\"height\":2368}"
        },
        {
            "src": "https://copyright.bdstatic.com/627514531,1164999862.jpg@w_640|wm_1,k_YmpoX3F1YW5qaW5nd2F0ZXIucG5n",
            "img_attr": "{\"width\":5184,\"height\":3456}"
        },
        {
            "src": "https://copyright.bdstatic.com/2074355754,547014243.jpg@w_640|wm_1,k_YmpoX3F1YW5qaW5nd2F0ZXIucG5n",
            "img_attr": "{\"width\":3984,\"height\":2656}"
        },
        {
            "src": "https://copyright.bdstatic.com/1522977867,2232302688.jpg@w_640|wm_1,k_YmpoX3F1YW5qaW5nd2F0ZXIucG5n",
            "img_attr": "{\"width\":4032,\"height\":3024}"
        },
        {
            "src": "https://copyright.bdstatic.com/3914869788,1287922873.jpg@w_640|wm_1,k_YmpoX3F1YW5qaW5nd2F0ZXIucG5n",
            "img_attr": "{\"width\":4320,\"height\":3317}"
        },
        {
            "src": "https://copyright.bdstatic.com/3502911356,1511619437.jpg@w_640|wm_1,k_YmpoX3F1YW5qaW5nd2F0ZXIucG5n",
            "img_attr": "{\"width\":4000,\"height\":6000}"
        },
        {
            "src": "https://copyright.bdstatic.com/2185939722,3195674485.jpg@w_640|wm_1,k_YmpoX3F1YW5qaW5nd2F0ZXIucG5n",
            "img_attr": "{\"width\":2617,\"height\":5093}"
        }
    ]
}